harrier/__init__.py
harrier/assets.py
harrier/build.py
harrier/cli.py
harrier/common.py
harrier/config.py
harrier/data.py
harrier/dev.py
harrier/extensions.py
harrier/frontmatter.py
harrier/main.py
harrier/render.py
harrier/version.py
harrier-0.13.2.dist-info/LICENSE
harrier-0.13.2.dist-info/METADATA
harrier-0.13.2.dist-info/WHEEL
harrier-0.13.2.dist-info/entry_points.txt
harrier-0.13.2.dist-info/top_level.txt
harrier-0.13.2.dist-info/zip-safe
harrier-0.13.2.dist-info/RECORD
