Metadata-Version: 2.1
Name: harrier
Version: 0.13.2
Summary: Static site generator
Home-page: https://github.com/samuelcolvin/harrier
Author: Samuel Colvin
Author-email: s@muelcolvin.com
License: MIT
Keywords: css,sass,scss,jinja,jinja2,build,static,static site generator
Classifier: Development Status :: 4 - Beta
Classifier: Environment :: Console
Classifier: Environment :: Web Environment
Classifier: Intended Audience :: Developers
Classifier: License :: OSI Approved :: MIT License
Classifier: Programming Language :: Python
Classifier: Programming Language :: Python :: 3
Classifier: Programming Language :: Python :: 3 :: Only
Classifier: Programming Language :: Python :: 3.8
Classifier: Programming Language :: Python :: 3.9
Classifier: Programming Language :: Python :: 3.10
Classifier: Programming Language :: Python :: 3.11
Requires-Python: >=3.8
License-File: LICENSE
Requires-Dist: aiohttp >=3.8
Requires-Dist: aiohttp-devtools >=1.1
Requires-Dist: click >=7
Requires-Dist: devtools >=0.11
Requires-Dist: grablib >=0.8
Requires-Dist: Jinja2 >=3
Requires-Dist: libsass >=0.21
Requires-Dist: misaka >=2.1
Requires-Dist: pillow >=10.0
Requires-Dist: pydantic >=2.1.1
Requires-Dist: Pygments >=2.15
Requires-Dist: ruamel.yaml >=0.17
Requires-Dist: watchfiles >=0.19.0
